focus_stack/__init__.py
focus_stack/__main__.py
focus_stack/focus_stack.py
focus_stack/run.py
focus_stack-0.0.1.dist-info/LICENSE
focus_stack-0.0.1.dist-info/METADATA
focus_stack-0.0.1.dist-info/WHEEL
focus_stack-0.0.1.dist-info/entry_points.txt
focus_stack-0.0.1.dist-info/top_level.txt
focus_stack-0.0.1.dist-info/RECORD
