Metadata-Version: 2.1
Name: focus-stack
Version: 0.0.1
Summary: Tool to focus stack images.
Home-page: https://github.com/momonala/focus-stack
Author: Mohit Nalavadi
Author-email: mnalavadi@gmail.com
License: UNKNOWN
Platform: UNKNOWN
Classifier: Programming Language :: Python :: 3
Classifier: License :: OSI Approved :: MIT License
Classifier: Operating System :: OS Independent
Requires-Python: >=3.6
